LICENSE
README.md
setup.py
pyhuelights/__init__.py
pyhuelights/animations.py
pyhuelights/core.py
pyhuelights/discovery.py
pyhuelights/exceptions.py
pyhuelights/manager.py
pyhuelights/registration.py
pyhuelights.egg-info/PKG-INFO
pyhuelights.egg-info/SOURCES.txt
pyhuelights.egg-info/dependency_links.txt
pyhuelights.egg-info/requires.txt
pyhuelights.egg-info/top_level.txt
tests/test_animations.py
tests/test_core.py
tests/test_discovery.py
tests/test_manager.py
tests/test_registration.py