Metadata-Version: 2.1
Name: pyhuelights
Version: 0.8.2
Summary: Library to remote control Philips Hue Lights
Author: Srivatsan Iyer
Author-email: supersaiyanmode.rox@gmail.com
License: MIT
License-File: LICENSE
